[
  {
    "Rank": 1,
    "State": "California",
    "2018 Population": 39776830,
    "2018 Growth": 0.006074793432817804,
    "% of US": 0.12125883740009955
  },
  {
    "Rank": 2,
    "State": "Texas",
    "2018 Population": 28704330,
    "2018 Growth": 0.014122582777722714,
    "% of US": 0.08750455187476729
  },
  {
    "Rank": 3,
    "State": "Florida",
    "2018 Population": 21312211,
    "2018 Growth": 0.015621652275023434,
    "% of US": 0.0649698311375143
  },
  {
    "Rank": 4,
    "State": "New York",
    "2018 Population": 19862512,
    "2018 Growth": 0.0006606245357856366,
    "% of US": 0.06055045394430693
  },
  {
    "Rank": 5,
    "State": "Pennsylvania",
    "2018 Population": 12823989,
    "2018 Growth": 0.0014409391812306716,
    "% of US": 0.039093663244951025
  },
  {
    "Rank": 6,
    "State": "Illinois",
    "2018 Population": 12768320,
    "2018 Growth": -0.00263263079592968,
    "% of US": 0.0389239574584611
  },
  {
    "Rank": 7,
    "State": "Ohio",
    "2018 Population": 11694664,
    "2018 Growth": 0.003092564473171633,
    "% of US": 0.0356509395149085
  },
  {
    "Rank": 8,
    "State": "Georgia",
    "2018 Population": 10545138,
    "2018 Growth": 0.011099318569207206,
    "% of US": 0.03214663345730695
  },
  {
    "Rank": 9,
    "State": "North Carolina",
    "2018 Population": 10390149,
    "2018 Growth": 0.011362332247910834,
    "% of US": 0.03167415272041052
  },
  {
    "Rank": 10,
    "State": "Michigan",
    "2018 Population": 9991177,
    "2018 Growth": 0.00289752046488001,
    "% of US": 0.030457894892041783
  },
  {
    "Rank": 11,
    "State": "New Jersey",
    "2018 Population": 9032872,
    "2018 Growth": 0.0030234373022073324,
    "% of US": 0.027536522068347627
  },
  {
    "Rank": 12,
    "State": "Virginia",
    "2018 Population": 8525660,
    "2018 Growth": 0.006569051785001667,
    "% of US": 0.025990296855444055
  },
  {
    "Rank": 13,
    "State": "Washington",
    "2018 Population": 7530552,
    "2018 Growth": 0.016853001785236188,
    "% of US": 0.022956730853137226
  },
  {
    "Rank": 14,
    "State": "Arizona",
    "2018 Population": 7123898,
    "2018 Growth": 0.015339774552575625,
    "% of US": 0.021717054607843168
  },
  {
    "Rank": 15,
    "State": "Massachusetts",
    "2018 Population": 6895917,
    "2018 Growth": 0.005262237968669536,
    "% of US": 0.02102205927992709
  },
  {
    "Rank": 16,
    "State": "Tennessee",
    "2018 Population": 6782564,
    "2018 Growth": 0.00991366268889271,
    "% of US": 0.02067650502143506
  },
  {
    "Rank": 17,
    "State": "Indiana",
    "2018 Population": 6699629,
    "2018 Growth": 0.004921538281080995,
    "% of US": 0.020423679402103975
  },
  {
    "Rank": 18,
    "State": "Missouri",
    "2018 Population": 6135888,
    "2018 Growth": 0.0036568059184118873,
    "% of US": 0.018705126710630838
  },
  {
    "Rank": 19,
    "State": "Maryland",
    "2018 Population": 6079602,
    "2018 Growth": 0.004531427286412759,
    "% of US": 0.01853354001249773
  },
  {
    "Rank": 20,
    "State": "Wisconsin",
    "2018 Population": 5818049,
    "2018 Growth": 0.0038937220590586907,
    "% of US": 0.017736201142142593
  },
  {
    "Rank": 21,
    "State": "Colorado",
    "2018 Population": 5684203,
    "2018 Growth": 0.013741195622592128,
    "% of US": 0.017328174400176134
  },
  {
    "Rank": 22,
    "State": "Minnesota",
    "2018 Population": 5628162,
    "2018 Growth": 0.009245049766829494,
    "% of US": 0.017157334579437807
  },
  {
    "Rank": 23,
    "State": "South Carolina",
    "2018 Population": 5088916,
    "2018 Growth": 0.012846787327921216,
    "% of US": 0.015513454385046898
  },
  {
    "Rank": 24,
    "State": "Alabama",
    "2018 Population": 4888949,
    "2018 Growth": 0.002913381966284545,
    "% of US": 0.014903859152385429
  },
  {
    "Rank": 25,
    "State": "Louisiana",
    "2018 Population": 4682509,
    "2018 Growth": -0.00038938307759073254,
    "% of US": 0.014274531114105943
  },
  {
    "Rank": 26,
    "State": "Kentucky",
    "2018 Population": 4472265,
    "2018 Growth": 0.00405820229002396,
    "% of US": 0.013633606661092807
  },
  {
    "Rank": 27,
    "State": "Oregon",
    "2018 Population": 4199563,
    "2018 Growth": 0.013707475374000522,
    "% of US": 0.01280228029655642
  },
  {
    "Rank": 28,
    "State": "Oklahoma",
    "2018 Population": 3940521,
    "2018 Growth": 0.0024567118068699045,
    "% of US": 0.012012596157377993
  },
  {
    "Rank": 29,
    "State": "Connecticut",
    "2018 Population": 3588683,
    "2018 Growth": 0.00013906756175274815,
    "% of US": 0.010940025345848361
  },
  {
    "Rank": 30,
    "State": "Iowa",
    "2018 Population": 3160553,
    "2018 Growth": 0.00471817023242127,
    "% of US": 0.009634879962063261
  },
  {
    "Rank": 31,
    "State": "Utah",
    "2018 Population": 3159345,
    "2018 Growth": 0.018541294776346806,
    "% of US": 0.00963119739923512
  },
  {
    "Rank": 32,
    "State": "Nevada",
    "2018 Population": 3056824,
    "2018 Growth": 0.0196078169763636,
    "% of US": 0.009318664267029875
  },
  {
    "Rank": 33,
    "State": "Arkansas",
    "2018 Population": 3020327,
    "2018 Growth": 0.005341714268215503,
    "% of US": 0.009207403923040888
  },
  {
    "Rank": 34,
    "State": "Mississippi",
    "2018 Population": 2982785,
    "2018 Growth": -0.00044066887838878355,
    "% of US": 0.009092957918327225
  },
  {
    "Rank": 35,
    "State": "Kansas",
    "2018 Population": 2918515,
    "2018 Growth": 0.0018509345468762373,
    "% of US": 0.00889703216256176
  },
  {
    "Rank": 36,
    "State": "New Mexico",
    "2018 Population": 2090708,
    "2018 Growth": 0.0012633676074078615,
    "% of US": 0.006373479772598453
  },
  {
    "Rank": 37,
    "State": "Nebraska",
    "2018 Population": 1932549,
    "2018 Growth": 0.006496097029492498,
    "% of US": 0.005891335356757313
  },
  {
    "Rank": 38,
    "State": "West Virginia",
    "2018 Population": 1803077,
    "2018 Growth": -0.007037999137597284,
    "% of US": 0.005496642662647056
  },
  {
    "Rank": 39,
    "State": "Idaho",
    "2018 Population": 1753860,
    "2018 Growth": 0.021501587414375356,
    "% of US": 0.005346605663712734
  },
  {
    "Rank": 40,
    "State": "Hawaii",
    "2018 Population": 1426393,
    "2018 Growth": -0.0008020802248346337,
    "% of US": 0.0043483293378492
  },
  {
    "Rank": 41,
    "State": "New Hampshire",
    "2018 Population": 1350575,
    "2018 Growth": 0.005793885142557187,
    "% of US": 0.0041171997447166965
  },
  {
    "Rank": 42,
    "State": "Maine",
    "2018 Population": 1341582,
    "2018 Growth": 0.004248050201099307,
    "% of US": 0.0040897847716095115
  },
  {
    "Rank": 43,
    "State": "Montana",
    "2018 Population": 1062330,
    "2018 Growth": 0.011268042718989957,
    "% of US": 0.003238490868559605
  },
  {
    "Rank": 44,
    "State": "Rhode Island",
    "2018 Population": 1061712,
    "2018 Growth": 0.00195632663576939,
    "% of US": 0.0032366069084372607
  },
  {
    "Rank": 45,
    "State": "Delaware",
    "2018 Population": 971180,
    "2018 Growth": 0.009606638258766953,
    "% of US": 0.0029606219929096582
  },
  {
    "Rank": 46,
    "State": "South Dakota",
    "2018 Population": 877790,
    "2018 Growth": 0.009341517318142811,
    "% of US": 0.0026759245239360045
  },
  {
    "Rank": 47,
    "State": "North Dakota",
    "2018 Population": 755238,
    "2018 Growth": -0.00020519120510775757,
    "% of US": 0.002302327305629342
  },
  {
    "Rank": 48,
    "State": "Alaska",
    "2018 Population": 738068,
    "2018 Growth": -0.002334430484120631,
    "% of US": 0.002249984918411464
  },
  {
    "Rank": 49,
    "State": "District of Columbia",
    "2018 Population": 703608,
    "2018 Growth": 0.013885286438069633,
    "% of US": 0.0021449343264762235
  },
  {
    "Rank": 50,
    "State": "Vermont",
    "2018 Population": 623960,
    "2018 Growth": 0.0004858439815476068,
    "% of US": 0.0019021290581518464
  },
  {
    "Rank": 51,
    "State": "Wyoming",
    "2018 Population": 573720,
    "2018 Growth": -0.009657958105693809,
    "% of US": 0.0017489734650344211
  }
]